{"status":"done","chunks":{"dashboard":[{"name":"dashboard.js","path":"C:\\123\\Flask-development\\Games_ecommerce\\games_ecommerce\\assets\\bundles\\dashboard.js"}],"most_bought_products":[{"name":"most_bought_products.js","path":"C:\\123\\Flask-development\\Games_ecommerce\\games_ecommerce\\assets\\bundles\\most_bought_products.js"}],"orders_per_day":[{"name":"orders_per_day.js","path":"C:\\123\\Flask-development\\Games_ecommerce\\games_ecommerce\\assets\\bundles\\orders_per_day.js"}]},"error":"ModuleBuildError","message":"Module build failed (from ./node_modules/babel-loader/lib/index.js):\nSyntaxError: C:\\123\\Flask-development\\Games_ecommerce\\games_ecommerce\\frontend\\src\\OrderLineStatusSelect.js: Unexpected token, expected \"...\" (83:54)\n\n  81 |           order_id={props.order_id}\n  82 |           value={props.orderLineStatus}\n> 83 |           {/*disabled={props.orderLineStatus === 20}*/}\n     |                                                       ^\n  84 |           onChange={(e) => {\n  85 |             updateOrderLine(e, props.id)\n  86 |             .then(response => {\n    at Object._raise (C:\\123\\Flask-development\\Games_ecommerce\\games_ecommerce\\frontend\\node_modules\\@babel\\parser\\lib\\index.js:757:17)\n    at Object.raiseWithData (C:\\123\\Flask-development\\Games_ecommerce\\games_ecommerce\\frontend\\node_modules\\@babel\\parser\\lib\\index.js:750:17)\n    at Object.raise (C:\\123\\Flask-development\\Games_ecommerce\\games_ecommerce\\frontend\\node_modules\\@babel\\parser\\lib\\index.js:744:17)\n    at Object.unexpected (C:\\123\\Flask-development\\Games_ecommerce\\games_ecommerce\\frontend\\node_modules\\@babel\\parser\\lib\\index.js:8834:16)\n    at Object.expect (C:\\123\\Flask-development\\Games_ecommerce\\games_ecommerce\\frontend\\node_modules\\@babel\\parser\\lib\\index.js:8820:28)\n    at Object.jsxParseAttribute (C:\\123\\Flask-development\\Games_ecommerce\\games_ecommerce\\frontend\\node_modules\\@babel\\parser\\lib\\index.js:4510:12)\n    at Object.jsxParseOpeningElementAfterName (C:\\123\\Flask-development\\Games_ecommerce\\games_ecommerce\\frontend\\node_modules\\@babel\\parser\\lib\\index.js:4537:28)\n    at Object.jsxParseOpeningElementAt (C:\\123\\Flask-development\\Games_ecommerce\\games_ecommerce\\frontend\\node_modules\\@babel\\parser\\lib\\index.js:4530:17)\n    at Object.jsxParseElementAt (C:\\123\\Flask-development\\Games_ecommerce\\games_ecommerce\\frontend\\node_modules\\@babel\\parser\\lib\\index.js:4562:33)\n    at Object.jsxParseElementAt (C:\\123\\Flask-development\\Games_ecommerce\\games_ecommerce\\frontend\\node_modules\\@babel\\parser\\lib\\index.js:4578:32)\n    at Object.jsxParseElementAt (C:\\123\\Flask-development\\Games_ecommerce\\games_ecommerce\\frontend\\node_modules\\@babel\\parser\\lib\\index.js:4578:32)\n    at Object.jsxParseElement (C:\\123\\Flask-development\\Games_ecommerce\\games_ecommerce\\frontend\\node_modules\\@babel\\parser\\lib\\index.js:4636:17)\n    at Object.parseExprAtom (C:\\123\\Flask-development\\Games_ecommerce\\games_ecommerce\\frontend\\node_modules\\@babel\\parser\\lib\\index.js:4643:19)\n    at Object.parseExprSubscripts (C:\\123\\Flask-development\\Games_ecommerce\\games_ecommerce\\frontend\\node_modules\\@babel\\parser\\lib\\index.js:9688:23)\n    at Object.parseMaybeUnary (C:\\123\\Flask-development\\Games_ecommerce\\games_ecommerce\\frontend\\node_modules\\@babel\\parser\\lib\\index.js:9668:21)\n    at Object.parseExprOps (C:\\123\\Flask-development\\Games_ecommerce\\games_ecommerce\\frontend\\node_modules\\@babel\\parser\\lib\\index.js:9538:23)\n    at Object.parseMaybeConditional (C:\\123\\Flask-development\\Games_ecommerce\\games_ecommerce\\frontend\\node_modules\\@babel\\parser\\lib\\index.js:9511:23)\n    at Object.parseMaybeAssign (C:\\123\\Flask-development\\Games_ecommerce\\games_ecommerce\\frontend\\node_modules\\@babel\\parser\\lib\\index.js:9466:21)\n    at Object.parseParenAndDistinguishExpression (C:\\123\\Flask-development\\Games_ecommerce\\games_ecommerce\\frontend\\node_modules\\@babel\\parser\\lib\\index.js:10313:28)\n    at Object.parseExprAtom (C:\\123\\Flask-development\\Games_ecommerce\\games_ecommerce\\frontend\\node_modules\\@babel\\parser\\lib\\index.js:10042:21)\n    at Object.parseExprAtom (C:\\123\\Flask-development\\Games_ecommerce\\games_ecommerce\\frontend\\node_modules\\@babel\\parser\\lib\\index.js:4648:20)\n    at Object.parseExprSubscripts (C:\\123\\Flask-development\\Games_ecommerce\\games_ecommerce\\frontend\\node_modules\\@babel\\parser\\lib\\index.js:9688:23)\n    at Object.parseMaybeUnary (C:\\123\\Flask-development\\Games_ecommerce\\games_ecommerce\\frontend\\node_modules\\@babel\\parser\\lib\\index.js:9668:21)\n    at Object.parseExprOps (C:\\123\\Flask-development\\Games_ecommerce\\games_ecommerce\\frontend\\node_modules\\@babel\\parser\\lib\\index.js:9538:23)\n    at Object.parseMaybeConditional (C:\\123\\Flask-development\\Games_ecommerce\\games_ecommerce\\frontend\\node_modules\\@babel\\parser\\lib\\index.js:9511:23)\n    at Object.parseMaybeAssign (C:\\123\\Flask-development\\Games_ecommerce\\games_ecommerce\\frontend\\node_modules\\@babel\\parser\\lib\\index.js:9466:21)\n    at Object.parseExpression (C:\\123\\Flask-development\\Games_ecommerce\\games_ecommerce\\frontend\\node_modules\\@babel\\parser\\lib\\index.js:9418:23)\n    at Object.parseReturnStatement (C:\\123\\Flask-development\\Games_ecommerce\\games_ecommerce\\frontend\\node_modules\\@babel\\parser\\lib\\index.js:11577:28)\n    at Object.parseStatementContent (C:\\123\\Flask-development\\Games_ecommerce\\games_ecommerce\\frontend\\node_modules\\@babel\\parser\\lib\\index.js:11258:21)\n    at Object.parseStatement (C:\\123\\Flask-development\\Games_ecommerce\\games_ecommerce\\frontend\\node_modules\\@babel\\parser\\lib\\index.js:11210:17)"}